tweaker/FileHandler.py
tweaker/MeshTweaker.py
tweaker/ThreeMF.py
tweaker/Tweaker.py
tweaker/__init__.py
tweaker/test.py
tweaker/test_Tweaker.py
python2C-0.0.1.dist-info/METADATA
python2C-0.0.1.dist-info/WHEEL
python2C-0.0.1.dist-info/top_level.txt
python2C-0.0.1.dist-info/RECORD
