Metadata-Version: 2.1
Name: python2C
Version: 0.0.1
Summary: tweaker python to be used in c++
License: UNKNOWN
Platform: UNKNOWN
